apilot/__init__.py
apilot/version.py
apilot/core/__init__.py
apilot/core/constant.py
apilot/core/event.py
apilot/core/models.py
apilot/datafeed/__init__.py
apilot/datafeed/csv_provider.py
apilot/datafeed/database.py
apilot/engine/__init__.py
apilot/engine/backtest.py
apilot/engine/base_engine.py
apilot/engine/live.py
apilot/engine/main_engine.py
apilot/engine/oms_engine.py
apilot/gateway/__init__.py
apilot/gateway/binance.py
apilot/gateway/gateway.py
apilot/optimizer/__init__.py
apilot/optimizer/gridoptimizer.py
apilot/optimizer/settings.py
apilot/performance/__init__.py
apilot/performance/aisummary.py
apilot/performance/calculator.py
apilot/performance/plot.py
apilot/performance/report.py
apilot/strategy/__init__.py
apilot/strategy/pa_template.py
apilot/utils/__init__.py
apilot/utils/array_manager.py
apilot/utils/bar_generator.py
apilot/utils/logger.py
apilot/utils/utility.py
apilot-0.1.32.dist-info/licenses/LICENSE
apilot-0.1.32.dist-info/METADATA
apilot-0.1.32.dist-info/WHEEL
apilot-0.1.32.dist-info/top_level.txt
apilot-0.1.32.dist-info/RECORD
