Metadata-Version: 2.4
Name: apilot
Version: 0.1.32
Summary: AI-Driven Qutan, Open to All
Author-email: AlphaPilot <contact@alphapilot.tech>
License: MIT
Project-URL: Homepage, https://github.com/AlphaPilotHQ/apilot
Project-URL: Documentation, https://github.com/AlphaPilotHQ/apilot/wiki
Project-URL: Repository, https://github.com/AlphaPilotHQ/apilot
Project-URL: Issues, https://github.com/AlphaPilotHQ/apilot/issues
Requires-Python: >=3.10
License-File: LICENSE
Requires-Dist: numpy
Requires-Dist: pandas
Requires-Dist: plotly
Requires-Dist: tqdm
Requires-Dist: ccxt
Requires-Dist: python-dotenv
Provides-Extra: dev
Requires-Dist: pytest; extra == "dev"
Requires-Dist: pytest-cov; extra == "dev"
Requires-Dist: ruff; extra == "dev"
Provides-Extra: all
Requires-Dist: pytest; extra == "all"
Requires-Dist: pytest-cov; extra == "all"
Requires-Dist: ruff; extra == "all"
Dynamic: license-file
